gateway/BENCHMARKS.md
gateway/CLAUDE_CODE_INTEGRATION.md
gateway/PERFORMANCE_SUMMARY.md
gateway/README.md
gateway/__init__.py
gateway/__version__.py
gateway/benchmark_results.json
gateway/benchmark_results_comprehensive.json
gateway/benchmarks.py
gateway/imessage_client.py
src/__init__.py
src/contacts_manager.py
src/contacts_sync.py
src/drafting.py
src/messages_interface.py
src/scheduler.py
src/style_analyzer.py
src/templates.py
src/rag/__init__.py
src/rag/chunker.py
src/rag/store.py
src/rag/unified/__init__.py
src/rag/unified/base_indexer.py
src/rag/unified/calendar_indexer.py
src/rag/unified/chunk.py
src/rag/unified/gmail_indexer.py
src/rag/unified/imessage_indexer.py
src/rag/unified/index_state.py
src/rag/unified/notes_indexer.py
src/rag/unified/retriever.py
src/rag/unified/slack_indexer.py
src/rag/unified/store.py
src/rag/unified/superwhisper_indexer.py
wolfies_imessage_gateway-4.0.0.dist-info/METADATA
wolfies_imessage_gateway-4.0.0.dist-info/WHEEL
wolfies_imessage_gateway-4.0.0.dist-info/entry_points.txt
wolfies_imessage_gateway-4.0.0.dist-info/licenses/LICENSE
wolfies_imessage_gateway-4.0.0.dist-info/RECORD
