Metadata-Version: 2.4
Name: wolfies-imessage-gateway
Version: 4.0.0
Summary: Wolfie's iMessage Gateway - Direct CLI 19x faster than MCP alternatives
Project-URL: Homepage, https://github.com/wolfiesch/wolfies-imessage-gateway
Project-URL: Repository, https://github.com/wolfiesch/wolfies-imessage-gateway
Project-URL: Benchmark, https://github.com/wolfiesch/wolfies-imessage-gateway/blob/main/PERFORMANCE_COMPARISON.md
Author: Wolfgang Schoenberger
License: MIT
License-File: LICENSE
Keywords: claude-code,gateway-pattern,imessage,macos,messaging,wolfies
Requires-Python: >=3.9
Requires-Dist: chromadb>=0.4.0
Requires-Dist: fuzzywuzzy>=0.18.0
Requires-Dist: python-levenshtein>=0.20.0
Requires-Dist: rich>=13.0.0
Requires-Dist: sentence-transformers>=2.2.0
Provides-Extra: dev
Requires-Dist: black>=23.0.0; extra == 'dev'
Requires-Dist: pylint>=3.0.0; extra == 'dev'
Requires-Dist: pytest-cov>=4.1.0; extra == 'dev'
Requires-Dist: pytest>=7.4.0; extra == 'dev'
